gocept.runner-3.0-py3.11-nspkg.pth
gocept/runner/README.rst
gocept/runner/__init__.py
gocept/runner/appmain.rst
gocept/runner/example.py
gocept/runner/ftesting.zcml
gocept/runner/once.rst
gocept/runner/runner.py
gocept/runner/testing.py
gocept/runner/transaction.py
gocept/runner/transaction.rst
gocept/runner/tests/__init__.py
gocept/runner/tests/test_doctests.py
gocept/runner/tests/test_runner.py
gocept/runner/tests/test_transaction.py
gocept.runner-3.0.dist-info/LICENSE.txt
gocept.runner-3.0.dist-info/METADATA
gocept.runner-3.0.dist-info/WHEEL
gocept.runner-3.0.dist-info/entry_points.txt
gocept.runner-3.0.dist-info/namespace_packages.txt
gocept.runner-3.0.dist-info/top_level.txt
gocept.runner-3.0.dist-info/RECORD
