Metadata-Version: 2.1
Name: gocept.runner
Version: 3.0
Summary: Create stand alone programs with full Zope3 runtime environment
Home-page: https://github.com/gocept/gocept.runner
Author: gocept gmbh & co. kg
Author-email: mail@gocept.com
License: ZPL 2.1
Keywords: zope3 mainloop
Classifier: Topic :: Software Development
Classifier: Framework :: Zope :: 3
Classifier: Development Status :: 5 - Production/Stable
Classifier: Intended Audience :: Developers
Classifier: License :: OSI Approved
Classifier: License :: OSI Approved :: Zope Public License
Classifier: Natural Language :: English
Classifier: Operating System :: OS Independent
Classifier: Programming Language :: Python
Classifier: Programming Language :: Python :: 3
Classifier: Programming Language :: Python :: 3.7
Classifier: Programming Language :: Python :: 3.8
Classifier: Programming Language :: Python :: 3.9
Classifier: Programming Language :: Python :: 3.10
Classifier: Programming Language :: Python :: 3.11
Requires-Python: >=3.7
License-File: LICENSE.txt
Requires-Dist: ZODB
Requires-Dist: decorator
Requires-Dist: setuptools
Requires-Dist: transaction
Requires-Dist: zope.app.appsetup (>=3.6.0)
Requires-Dist: zope.app.wsgi
Requires-Dist: zope.authentication
Requires-Dist: zope.component
Requires-Dist: zope.publisher
Requires-Dist: zope.security
Requires-Dist: zope.testing
Provides-Extra: test
Requires-Dist: gocept.testing (>=1.1) ; extra == 'test'
Requires-Dist: mock ; extra == 'test'
Requires-Dist: zope.app.appsetup (>=3.6.0) ; extra == 'test'
Requires-Dist: zope.app.testing ; extra == 'test'
Requires-Dist: zope.app.zcmlfiles ; extra == 'test'
Requires-Dist: zope.securitypolicy ; extra == 'test'
